nuset/__init__.py
nuset/layers/__init__.py
nuset/layers/anchor_size.py
nuset/layers/compute_metrics.py
nuset/layers/marker_watershed.py
nuset/layers/model_RPN.py
nuset/layers/models.py
nuset/layers/rpn_loss.py
nuset/layers/rpn_proposal.py
nuset/layers/rpn_target.py
nuset/layers/seg_loss.py
nuset/models/__init__.py
nuset/models/bases.py
nuset/models/nuset.py
nuset/network/__init__.py
nuset/network/foreground.ckpt.index
nuset/network/foreground.ckpt.meta
nuset/network/whole_norm.ckpt.index
nuset/network/whole_norm.ckpt.meta
nuset/utils/__init__.py
nuset/utils/anchors.py
nuset/utils/bbox_overlap.py
nuset/utils/bbox_transform.py
nuset/utils/bbox_transform_tf.py
nuset/utils/config.py
nuset/utils/generate_anchors.py
nuset/utils/image_vis.py
nuset/utils/load_data.py
nuset/utils/load_data_exp.py
nuset/utils/losses.py
nuset/utils/normalization.py
nuset/utils/tf_utils.py
nuset_lib-0.2.0.dist-info/LICENSE
nuset_lib-0.2.0.dist-info/METADATA
nuset_lib-0.2.0.dist-info/WHEEL
nuset_lib-0.2.0.dist-info/top_level.txt
nuset_lib-0.2.0.dist-info/RECORD
